{
    "small-square": {
        "squares": [909, 910, 1009, 1010],
        "points": 15,
        "displayName": "Small square",
        "completed": false
    },
    "large-square": {
        "squares": [909, 910, 911, 1009, 1010, 1011, 1109, 1110, 1111],
        "points": 50,
        "displayName": "Large square",
        "completed": false
    },
    "hollow-square": {
        "squares": [909, 910, 911, 1011, 1111, 1110, 1109, 1009],
        "points": 65,
        "displayName": "Hollow square",
        "completed": false
    },
    "small-l": {
        "squares": [909, 1009, 1010],
        "points": 10,
        "displayName": "Small 'L'",
        "completed": false
    },
    "large-l": {
        "squares": [909, 1009, 1109, 1110, 1111],
        "points": 35,
        "displayName": "Large 'L'",
        "completed": false
    },
    "thick-l": {
        "squares": [909, 910, 1009, 1010, 1109, 1110, 1111, 1112, 1209, 1210, 1211, 1212],
        "points": 35,
        "displayName": "Thick 'L'",
        "completed": false
    },
    "stairs-right": {
        "squares": [909, 1009, 1010, 1109, 1110, 1111],
        "points": 45,
        "displayName": "Right stairs",
        "completed": false
    }
}